fenics_pulse-2025.0.0.dist-info/licenses/LICENSE
pulse/__init__.py
pulse/dolfin_utils.py
pulse/geometry.py
pulse/geometry_utils.py
pulse/io_utils.py
pulse/iterate.py
pulse/kinematics.py
pulse/mechanicsproblem.py
pulse/numpy_mpi.py
pulse/solver.py
pulse/unloader.py
pulse/unloading_utils.py
pulse/utils.py
pulse/example_meshes/__init__.py
pulse/material/__init__.py
pulse/material/active_model.py
pulse/material/guccione.py
pulse/material/holzapfelogden.py
pulse/material/linearelastic.py
pulse/material/material_model.py
pulse/material/neohookean.py
pulse/material/stvenantkirchhoff.py
fenics_pulse-2025.0.0.dist-info/METADATA
fenics_pulse-2025.0.0.dist-info/WHEEL
fenics_pulse-2025.0.0.dist-info/top_level.txt
fenics_pulse-2025.0.0.dist-info/RECORD
