Metadata-Version: 2.4
Name: fenics_pulse
Version: 2025.0.0
Summary: A python library based on FEniCS that aims to solve problems in continuum mechanics, in particular cardiac mechanics
Author-email: Henrik Finsberg <henriknf@simula.no>
License:                    GNU LESSER GENERAL PUBLIC LICENSE
Project-URL: Homepage, https://finsberg.github.io/pulse/
Project-URL: Documentation, https://finsberg.github.io/pulse/
Project-URL: Source, https://github.com/finsberg/pulse
Project-URL: Tracker, https://github.com/finsberg/pulse/issues
Keywords: finite element,mechanics,cardiac,heart
License-File: LICENSE
Requires-Dist: daiquiri
Requires-Dist: h5py
Requires-Dist: numpy
Requires-Dist: scipy
Provides-Extra: dev
Requires-Dist: bump2version; extra == "dev"
Requires-Dist: ipython; extra == "dev"
Requires-Dist: pdbpp; extra == "dev"
Requires-Dist: pre-commit; extra == "dev"
Provides-Extra: docs
Requires-Dist: jupyter-book; extra == "docs"
Requires-Dist: sphinxcontrib-bibtex; extra == "docs"
Provides-Extra: mesh
Requires-Dist: gmsh; extra == "mesh"
Requires-Dist: ldrb; extra == "mesh"
Requires-Dist: meshio; extra == "mesh"
Provides-Extra: plot
Requires-Dist: fenics-plotly; extra == "plot"
Requires-Dist: matplotlib; extra == "plot"
Provides-Extra: test
Requires-Dist: jupytext; extra == "test"
Requires-Dist: pytest; extra == "test"
Requires-Dist: fenics-plotly; extra == "test"
Requires-Dist: pytest-cov; extra == "test"
Requires-Dist: pytest-env; extra == "test"
Requires-Dist: cardiac-geometries>=1.1.2; extra == "test"
Provides-Extra: all
Requires-Dist: fenics-pulse[test]; extra == "all"
Requires-Dist: fenics-pulse[docs]; extra == "all"
Requires-Dist: fenics-pulse[mesh]; extra == "all"
Requires-Dist: fenics-pulse[dev]; extra == "all"
Dynamic: license-file
